assault/__init__.py
assault/cli.py
assault/config.py
assault/http.py
assault/stats.py
assault-1.0.0.dist-info/METADATA
assault-1.0.0.dist-info/WHEEL
assault-1.0.0.dist-info/entry_points.txt
assault-1.0.0.dist-info/top_level.txt
assault-1.0.0.dist-info/RECORD
