Metadata-Version: 2.1
Name: assault
Version: 1.0.0
Summary: A simple CLI load testing tool.
Home-page: https://arnabroy.github.io/assault.github.io/
Author: Arnab Roy
Author-email: arnabroy.007@gmail.com
License: MIT
Platform: UNKNOWN
Classifier: License :: OSI Approved :: MIT License
Classifier: Programming Language :: Python
Classifier: Programming Language :: Python :: 3
Classifier: Programming Language :: Python :: 3.7
Classifier: Programming Language :: Python :: Implementation :: CPython
Classifier: Programming Language :: Python :: Implementation :: PyPy
Requires-Python: >=3.7.0
Requires-Dist: click
Requires-Dist: requests
